{
	"partsInfo":[
		{"partsName":"frame",			"loadJson":"GameResult.json",				"partsType":"PARTS_SINGLE_DRAW",	"x": 640,	"y": 360},
		{"partsName":"scoreScene01",	"loadJson":"NumberCounterLarge.json",		"partsType":"PARTS_NUM_COUNTER",	"x": 1100,	"y": 243},
		{"partsName":"scoreScene02",	"loadJson":"NumberCounterLarge.json",		"partsType":"PARTS_NUM_COUNTER",	"x": 1100,	"y": 332},
		{"partsName":"scoreScene03",	"loadJson":"NumberCounterLarge.json",		"partsType":"PARTS_NUM_COUNTER",	"x": 1100,	"y": 410},
		{"partsName":"scoreTotal",		"loadJson":"NumberCounterLarge.json",		"partsType":"PARTS_NUM_COUNTER",	"x": 1100,	"y": 560}
	]
}